truthgit/__init__.py
truthgit/cli.py
truthgit/extractor.py
truthgit/fallacy_detector.py
truthgit/governance.py
truthgit/hashing.py
truthgit/hypothesis_tester.py
truthgit/logging_config.py
truthgit/mcp_server.py
truthgit/objects.py
truthgit/ontological_classifier.py
truthgit/proof.py
truthgit/repository.py
truthgit/sync.py
truthgit/validation.py
truthgit/validators.py
truthgit/api/__init__.py
truthgit/api/server.py
truthgit-0.6.0.dist-info/licenses/LICENSE
truthgit-0.6.0.dist-info/METADATA
truthgit-0.6.0.dist-info/WHEEL
truthgit-0.6.0.dist-info/entry_points.txt
truthgit-0.6.0.dist-info/top_level.txt
truthgit-0.6.0.dist-info/RECORD
