Metadata-Version: 2.4
Name: truthgit
Version: 0.6.0
Summary: Governance layer for autonomous agents
Author-email: TruthGit <hello@truthgit.com>
License: MIT
Project-URL: Homepage, https://truthgit.com
Project-URL: Documentation, https://truthgit.com/docs
Project-URL: Repository, https://github.com/truthgit/truthgit
Project-URL: Issues, https://github.com/truthgit/truthgit/issues
Keywords: truth,verification,consensus,llm,version-control
Classifier: Development Status :: 3 - Alpha
Classifier: Intended Audience :: Developers
Classifier: Intended Audience :: Science/Research
Classifier: License :: OSI Approved :: MIT License
Classifier: Programming Language :: Python :: 3
Classifier: Programming Language :: Python :: 3.10
Classifier: Programming Language :: Python :: 3.11
Classifier: Programming Language :: Python :: 3.12
Classifier: Topic :: Scientific/Engineering :: Artificial Intelligence
Classifier: Topic :: Software Development :: Version Control
Requires-Python: >=3.10
License-File: LICENSE
Requires-Dist: pydantic>=2.0.0
Requires-Dist: rich>=13.0.0
Requires-Dist: typer>=0.9.0
Requires-Dist: httpx>=0.25.0
Requires-Dist: python-dotenv>=1.0.0
Requires-Dist: cryptography>=41.0.0
Requires-Dist: mcp>=1.0.0
Requires-Dist: fastapi>=0.109.0
Requires-Dist: uvicorn>=0.27.0
Provides-Extra: local
Requires-Dist: ollama>=0.1.0; extra == "local"
Provides-Extra: cloud
Requires-Dist: anthropic>=0.40.0; extra == "cloud"
Requires-Dist: openai>=1.0.0; extra == "cloud"
Requires-Dist: google-generativeai>=0.3.0; extra == "cloud"
Provides-Extra: huggingface
Requires-Dist: transformers>=4.30.0; extra == "huggingface"
Requires-Dist: torch>=2.0.0; extra == "huggingface"
Requires-Dist: accelerate>=0.20.0; extra == "huggingface"
Provides-Extra: all
Requires-Dist: truthgit[cloud,huggingface,local]; extra == "all"
Provides-Extra: dev
Requires-Dist: pytest>=8.0.0; extra == "dev"
Requires-Dist: pytest-asyncio>=0.23.0; extra == "dev"
Requires-Dist: ruff>=0.1.0; extra == "dev"
Requires-Dist: mypy>=1.0.0; extra == "dev"
Dynamic: license-file
